flyteplugins/__init__.py
flyteplugins/vllm/__init__.py
flyteplugins/vllm/_app_environment.py
flyteplugins/vllm/_constants.py
flyteplugins/vllm/_model_loader/__init__.py
flyteplugins/vllm/_model_loader/shim.py
flyteplugins_vllm-2.0.0b53.dist-info/METADATA
flyteplugins_vllm-2.0.0b53.dist-info/WHEEL
flyteplugins_vllm-2.0.0b53.dist-info/entry_points.txt
flyteplugins_vllm-2.0.0b53.dist-info/top_level.txt
flyteplugins_vllm-2.0.0b53.dist-info/RECORD
