Metadata-Version: 2.4
Name: flyteplugins-vllm
Version: 2.0.0b53
Summary: vLLM plugin for flyte
Author-email: Niels Bantilan <cosmicbboy@users.noreply.github.com>
Requires-Python: >=3.10
Requires-Dist: flyte>=2.0.0b43
